MANIFEST.in
README.rst
setup.py
search_google/__init__.py
search_google/__main__.py
search_google/api.py
search_google/cli.py
search_google/config.json
search_google.egg-info/PKG-INFO
search_google.egg-info/SOURCES.txt
search_google.egg-info/dependency_links.txt
search_google.egg-info/entry_points.txt
search_google.egg-info/requires.txt
search_google.egg-info/top_level.txt