Metadata-Version: 1.1
Name: search-google
Version: 1.1.6
Summary: A command line tool and module for Google API web and image search.
Home-page: https://github.com/rrwen/search_google
Author: Richard Wen
Author-email: rrwen.dev@gmail.com
License: MIT
Download-URL: https://github.com/rrwen/search_google/archive/master.zip
Keywords: google,api,custom,web,image,search,engine,cli,cse,command,line,interface,tool,module
Platform: UNKNOWN
